Metadata-Version: 2.1
Name: botocore-refreshable-credentials
Version: 1.0.0
Summary: Implements a botocore.Session subclass for using botocore with expiring credentials (IAM STS)
Home-page: https://github.com/aweber/botocore-refreshable-credentials/
Author: Ryan Mclean
Author-email: aremm06@gmail.com
License: BSD 3-Clause License
Platform: UNKNOWN
Classifier: Development Status :: 5 - Production/Stable
Classifier: Framework :: AsyncIO
Classifier: Intended Audience :: Developers
Classifier: License :: OSI Approved :: BSD License
Classifier: Natural Language :: English
Classifier: Operating System :: OS Independent
Classifier: Programming Language :: Python :: 3
Classifier: Programming Language :: Python :: 3.8
Classifier: Programming Language :: Python :: 3.9
Classifier: Topic :: Communications
Classifier: Topic :: Internet
Classifier: Topic :: Software Development
Classifier: Typing :: Typed
Provides-Extra: testing
License-File: LICENSE
